mediator_lite/__init__.py
mediator_lite/base.py
mediator_lite/dispatcher.py
mediator_lite/py.typed
mediator_lite/registry.py
mediator_lite-0.1.0.dist-info/METADATA
mediator_lite-0.1.0.dist-info/WHEEL
mediator_lite-0.1.0.dist-info/licenses/LICENSE
mediator_lite-0.1.0.dist-info/RECORD
